interpretable_driving/__init__.py
interpretable_driving-0.0.1.dist-info/LICENSE
interpretable_driving-0.0.1.dist-info/METADATA
interpretable_driving-0.0.1.dist-info/WHEEL
interpretable_driving-0.0.1.dist-info/top_level.txt
interpretable_driving-0.0.1.dist-info/RECORD
